neuraltrust/__init__.py
neuraltrust/client.py
neuraltrust/config.py
neuraltrust/models.py
neuraltrust/transport.py
neuraltrust/processors/openai.py
neuraltrust-1.5.0.dist-info/licenses/LICENSE
neuraltrust-1.5.0.dist-info/METADATA
neuraltrust-1.5.0.dist-info/WHEEL
neuraltrust-1.5.0.dist-info/top_level.txt
neuraltrust-1.5.0.dist-info/RECORD
