Metadata-Version: 2.4
Name: neuraltrust
Version: 1.5.0
Summary: Python SDK for AI agent telemetry and observability
Author-email: Neuraltrust <support@neuraltrust.ai>
License: MIT
Project-URL: Homepage, https://neuraltrust.ai
Project-URL: Documentation, https://github.com/neuraltrust/neuraltrust-instrumentation#readme
Project-URL: Repository, https://github.com/neuraltrust/neuraltrust-instrumentation
Project-URL: Issues, https://github.com/neuraltrust/neuraltrust-instrumentation/issues
Keywords: ai,agents,telemetry,observability,monitoring,openai,llm,tracing
Classifier: Development Status :: 4 - Beta
Classifier: Intended Audience :: Developers
Classifier: License :: OSI Approved :: MIT License
Classifier: Programming Language :: Python :: 3
Classifier: Programming Language :: Python :: 3.9
Classifier: Programming Language :: Python :: 3.10
Classifier: Programming Language :: Python :: 3.11
Classifier: Programming Language :: Python :: 3.12
Classifier: Topic :: Software Development :: Libraries :: Python Modules
Classifier: Topic :: System :: Monitoring
Requires-Python: >=3.9
License-File: LICENSE
Requires-Dist: httpx>=0.26
Requires-Dist: openai-agents>=0.3.3
Requires-Dist: pydantic>=2.6
Requires-Dist: typing-extensions>=4.7
Provides-Extra: dev
Requires-Dist: pytest>=8.2; extra == "dev"
Requires-Dist: fastapi>=0.118; extra == "dev"
Requires-Dist: uvicorn[standard]>=0.37; extra == "dev"
Dynamic: license-file
